{
    "portfolio": [
        {
            "cover": "https://i.ibb.co/x2MdHXV/Open-Doors.jpg",
            "title": "Business Review Website",
            "description" : "Create, Review, Update, and Delete reviews. Built with React.",
            "url": "https://youtu.be/3bgmUNG4jx0",
            "url2": "https://github.com/AmazonSWCollab/OpenDoors"
        },
        {
            "cover": "https://i.ibb.co/zHxpj8y/titan-Radio.jpg",
            "title": "Music Player",
            "description" : "Player for CSUF's Radio Station. Built with JS, HTML, and CSS.",
            "url": "https://titanradio.org/live/",
            "url2": "https://github.com/Angel-Armendariz/TitanRadioLivePlayer"
        },
        {
          "cover": "https://i.ibb.co/y4jhcFs/shopping-cart.png",
          "title": "E-Commerce Website",
          "description": "Website with forum and shop. Built with PHP, MySQL, and CSS.",
          "url": "https://youtu.be/XO4u1DrO7A8",
          "url2": "https://github.com/cesar-gz/Shopping-cart"
        },
        {
            "cover": "https://i.ibb.co/4Scf7sz/Shark.jpg",
            "title": "Shark Website",
            "description" : "Website on the evolution of Sharks. Built with React.",
            "url": "https://cesar-gz.github.io/Sharks/",
            "url2": "https://github.com/cesar-gz/Sharks"
        },
        {
            "cover": "https://i.ibb.co/7ksC1Bp/alien-invasion.jpg",
            "title": "Alien-Invasion Game",
            "description" : "School Project to learn Python Programming. Built with Pygame.",
            "url" : "https://youtu.be/qwpuGuXqv9A",
            "url2": "https://github.com/cesar-gz/Alien-Invasion"
        }
    ]
}
